parcel_tracker_sdk/__init__.py
parcel_tracker_sdk/client.py
parcel_tracker_sdk/errors.py
parcel_tracker_sdk/models/__init__.py
parcel_tracker_sdk/models/recipient_models.py
parcel_tracker_sdk/services/recipients_service.py
parcel_tracker_sdk-0.1.0.dist-info/licenses/LICENSE
parcel_tracker_sdk-0.1.0.dist-info/METADATA
parcel_tracker_sdk-0.1.0.dist-info/WHEEL
parcel_tracker_sdk-0.1.0.dist-info/top_level.txt
parcel_tracker_sdk-0.1.0.dist-info/RECORD
